[
  {
    "source_book_id": 1,
    "source_chapter": 1,
    "source_verse_start": 1,
    "source_verse_end": 1,
    "target_book_id": 43,
    "target_chapter": 1,
    "target_verse_start": 1,
    "target_verse_end": 3,
    "weight": 1.0,
    "source": "TSK"
  },
  {
    "source_book_id": 1,
    "source_chapter": 1,
    "source_verse_start": 1,
    "source_verse_end": 1,
    "target_book_id": 19,
    "target_chapter": 33,
    "target_verse_start": 6,
    "target_verse_end": 6,
    "weight": 0.9,
    "source": "TSK"
  },
  {
    "source_book_id": 1,
    "source_chapter": 1,
    "source_verse_start": 1,
    "source_verse_end": 1,
    "target_book_id": 58,
    "target_chapter": 11,
    "target_verse_start": 3,
    "target_verse_end": 3,
    "weight": 0.85,
    "source": "TSK"
  },
  {
    "source_book_id": 1,
    "source_chapter": 1,
    "source_verse_start": 3,
    "source_verse_end": 3,
    "target_book_id": 19,
    "target_chapter": 33,
    "target_verse_start": 9,
    "target_verse_end": 9,
    "weight": 0.9,
    "source": "TSK"
  },
  {
    "source_book_id": 1,
    "source_chapter": 1,
    "source_verse_start": 3,
    "source_verse_end": 3,
    "target_book_id": 47,
    "target_chapter": 4,
    "target_verse_start": 6,
    "target_verse_end": 6,
    "weight": 0.85,
    "source": "TSK"
  },
  {
    "source_book_id": 1,
    "source_chapter": 1,
    "source_verse_start": 26,
    "source_verse_end": 27,
    "target_book_id": 1,
    "target_chapter": 5,
    "target_verse_start": 1,
    "target_verse_end": 2,
    "weight": 0.95,
    "source": "TSK"
  },
  {
    "source_book_id": 1,
    "source_chapter": 1,
    "source_verse_start": 27,
    "source_verse_end": 27,
    "target_book_id": 1,
    "target_chapter": 9,
    "target_verse_start": 6,
    "target_verse_end": 6,
    "weight": 0.9,
    "source": "TSK"
  },
  {
    "source_book_id": 43,
    "source_chapter": 1,
    "source_verse_start": 1,
    "source_verse_end": 1,
    "target_book_id": 1,
    "target_chapter": 1,
    "target_verse_start": 1,
    "target_verse_end": 1,
    "weight": 1.0,
    "source": "TSK"
  },
  {
    "source_book_id": 43,
    "source_chapter": 1,
    "source_verse_start": 1,
    "source_verse_end": 1,
    "target_book_id": 20,
    "target_chapter": 8,
    "target_verse_start": 22,
    "target_verse_end": 23,
    "weight": 0.9,
    "source": "TSK"
  },
  {
    "source_book_id": 43,
    "source_chapter": 1,
    "source_verse_start": 1,
    "source_verse_end": 1,
    "target_book_id": 62,
    "target_chapter": 1,
    "target_verse_start": 1,
    "target_verse_end": 2,
    "weight": 0.95,
    "source": "TSK"
  },
  {
    "source_book_id": 43,
    "source_chapter": 1,
    "source_verse_start": 3,
    "source_verse_end": 3,
    "target_book_id": 51,
    "target_chapter": 1,
    "target_verse_start": 16,
    "target_verse_end": 17,
    "weight": 0.95,
    "source": "TSK"
  },
  {
    "source_book_id": 43,
    "source_chapter": 1,
    "source_verse_start": 14,
    "source_verse_end": 14,
    "target_book_id": 50,
    "target_chapter": 2,
    "target_verse_start": 6,
    "target_verse_end": 8,
    "weight": 0.9,
    "source": "TSK"
  },
  {
    "source_book_id": 43,
    "source_chapter": 3,
    "source_verse_start": 16,
    "source_verse_end": 16,
    "target_book_id": 45,
    "target_chapter": 5,
    "target_verse_start": 8,
    "target_verse_end": 8,
    "weight": 1.0,
    "source": "TSK"
  },
  {
    "source_book_id": 43,
    "source_chapter": 3,
    "source_verse_start": 16,
    "source_verse_end": 16,
    "target_book_id": 62,
    "target_chapter": 4,
    "target_verse_start": 9,
    "target_verse_end": 10,
    "weight": 0.95,
    "source": "TSK"
  },
  {
    "source_book_id": 43,
    "source_chapter": 3,
    "source_verse_start": 16,
    "source_verse_end": 16,
    "target_book_id": 49,
    "target_chapter": 2,
    "target_verse_start": 4,
    "target_verse_end": 5,
    "weight": 0.9,
    "source": "TSK"
  },
  {
    "source_book_id": 43,
    "source_chapter": 3,
    "source_verse_start": 3,
    "source_verse_end": 3,
    "target_book_id": 60,
    "target_chapter": 1,
    "target_verse_start": 23,
    "target_verse_end": 23,
    "weight": 0.95,
    "source": "TSK"
  },
  {
    "source_book_id": 19,
    "source_chapter": 23,
    "source_verse_start": 1,
    "source_verse_end": 1,
    "target_book_id": 43,
    "target_chapter": 10,
    "target_verse_start": 11,
    "target_verse_end": 11,
    "weight": 1.0,
    "source": "TSK"
  },
  {
    "source_book_id": 19,
    "source_chapter": 23,
    "source_verse_start": 1,
    "source_verse_end": 1,
    "target_book_id": 66,
    "target_chapter": 7,
    "target_verse_start": 17,
    "target_verse_end": 17,
    "weight": 0.9,
    "source": "TSK"
  },
  {
    "source_book_id": 19,
    "source_chapter": 23,
    "source_verse_start": 4,
    "source_verse_end": 4,
    "target_book_id": 23,
    "target_chapter": 43,
    "target_verse_start": 2,
    "target_verse_end": 2,
    "weight": 0.85,
    "source": "TSK"
  },
  {
    "source_book_id": 19,
    "source_chapter": 1,
    "source_verse_start": 1,
    "source_verse_end": 1,
    "target_book_id": 24,
    "target_chapter": 17,
    "target_verse_start": 7,
    "target_verse_end": 8,
    "weight": 0.9,
    "source": "TSK"
  },
  {
    "source_book_id": 19,
    "source_chapter": 1,
    "source_verse_start": 2,
    "source_verse_end": 2,
    "target_book_id": 6,
    "target_chapter": 1,
    "target_verse_start": 8,
    "target_verse_end": 8,
    "weight": 0.85,
    "source": "TSK"
  },
  {
    "source_book_id": 19,
    "source_chapter": 119,
    "source_verse_start": 105,
    "source_verse_end": 105,
    "target_book_id": 20,
    "target_chapter": 6,
    "target_verse_start": 23,
    "target_verse_end": 23,
    "weight": 0.9,
    "source": "TSK"
  },
  {
    "source_book_id": 19,
    "source_chapter": 119,
    "source_verse_start": 105,
    "source_verse_end": 105,
    "target_book_id": 61,
    "target_chapter": 1,
    "target_verse_start": 19,
    "target_verse_end": 19,
    "weight": 0.85,
    "source": "TSK"
  }
]
